starbase/.DS_Store
starbase/__init__.py
starbase/cli.py
starbase/cli_better.py
starbase/cli_wrapper.py
starbase/core/.DS_Store
starbase/core/__init__.py
starbase/core/analysis.py
starbase/core/assignment.py
starbase/core/catalog.py
starbase/core/entry_points.py
starbase/core/extraction.py
starbase/core/file_search.py
starbase/core/menus.py
starbase/core/search.py
starbase/mcp_installer.py
starbase/mcp_server.py
starbase_code-1.0.1.dist-info/METADATA
starbase_code-1.0.1.dist-info/WHEEL
starbase_code-1.0.1.dist-info/entry_points.txt
starbase_code-1.0.1.dist-info/RECORD
