Metadata-Version: 2.1
Name: starbase-code
Version: 1.0.1
Summary: manage code from random folders into one central place
Author-Email: tsomerville2 <travis.somerville@gmail.com>
License: AGPL-3.0
Requires-Python: >=3.10
Requires-Dist: typer>=0.16.0
Requires-Dist: inquirerpy>=0.3.4
Requires-Dist: rich>=14.1.0
Requires-Dist: tinydb>=4.8.2
Requires-Dist: gitpython>=3.1.45
Requires-Dist: astor>=0.8.1
Requires-Dist: toml>=0.10.2
Requires-Dist: langchain>=0.3.27
Requires-Dist: langchain-groq>=0.3.6
Requires-Dist: langchain-anthropic>=0.3.17
Requires-Dist: ollama>=0.5.1
Requires-Dist: warpcoder>=0.3.6
Requires-Dist: behave>=1.2.6
Requires-Dist: watchdog>=6.0.0
Requires-Dist: radon>=6.0.1
Requires-Dist: editdistance>=0.8.1
Requires-Dist: mcp>=1.0.0
Requires-Dist: fastmcp>=2.11.3
Requires-Dist: pathspec>=0.12.1
